verilog/carryadder.v
module carryadder(s0, s1, s2, s3, c4, c0, a0, b0, a1, b1, a2, b2, a3, b3);

// Defining the inputs, outputs and wires of the carryadder
input c0, a0, b0, a1, b1, a2, b2, a3, b3;
output s0, s1, s2, s3, c4;

wire p0, g0, p1, g1, p2, g2, p3, g3, t1, t2, t3, t4,
    t5, t6, t7, t8, t9, t10, t11, t12, t13, t14, t15, t16;


// Defining the carryadder logic in blocks

// First, the carry-propogate and carry-generate block of the carryadder

// First digits
xor G1(p0, a0, b0);
and G2(g0, a0, b0);

// Second digits
xor G3(p1, a1, b1);
and G4(g1, a1, b1);

// Third digits
xor G5(p2, a2, b2);
and G6(g2, a2, b2);

// Fourth digits
xor G7(p3, a3, b3);
and G8(g3, a3, b3);

// Then, the carry-lookahead generator block of the carryadder

// C1
and G9(t1, p0, c0);
or G10(c1, g0, t1);

// C2
and G11(t2, p0, p1, c0);
and G12(t3, g0, p1);
or G13(t4, t3, G1);
or G14(c2, t2, t4);

// C3
and G15(t5, p0, p1, p2, c0);
and G16(t6, g0, p1, p2);
and G17(t7, g1, p2);
or G18(t8, g2, t7);
or G19(t9, t6, t8);
or G20(c3, t5, t9);

// C4
and G21(t10, p0, p1, p2, p3, c0);
and G22(t11, g0, p1, p2, p3);
and G23(t12, g1, p2, p3);
and G24(t13, g2, p3);
or G25(t14, g3, t13);
or G26(t15, t12, t14);
or G27(t16, t11, t15);
or G28(c4, t10, t16);

// Then the sum block of the carryadder

// S0
xor G29(s0, p0, c0);

// S1
xor G30(s1, p1, c1);

// S2
xor G31(s2, p2, c2);

// S3
xor G32(s3, p3, c3);

endmodule

verilog/testbench_cla.v
module testbench_cla;

reg c0, a0, b0, a1, b1, a2, b2, a3, b3;
wire s0, s1, s2, s3, c4;

carryadder test(s0, s1, s2, s3, c4, c0, a0, b0, a1, b1, a2, b2, a3, b3);

initial begin
    $dumpfile("test.vcd");
    $dumpvars(0, testbench_cla);
    $monitor($time, " c0 = %b, a0 = %b, b0 = %b, a1 = %b, b1 = %b, a2 = %b, b2 = %b, a3 = %b, b3 = %b",
    c0, a0, b0, a1, b1, a2, b2, a3, b3);

    c0 = 1'b0;
    a0 = 1'b0;
    b0 = 1'b0;
    a1 = 1'b0;
    b1 = 1'b0;
    a2 = 1'b0;
    b2 = 1'b0;
    a3 = 1'b0;
    b3 = 1'b0;

    #2560 $finish;

end

always #5 a0 = ~a0;
always #10 b0 = ~b0;
always #20 a1 = ~a1;
always #40 b1 = ~b1;
always #80 a2 = ~a2;
always #160 b2 = ~b2;
always #320 a3 = ~a3;
always #640 b3 = ~b3;
always #1280 c0 = ~c0;

endmodule

verilog/test.vcd
$date
	Thu Jan 27 01:46:11 2022
$end
$version
	Icarus Verilog
$end
$timescale
	1s
$end
$scope module testbench_cla $end
$var wire 1 ! s3 $end
$var wire 1 " s2 $end
$var wire 1 # s1 $end
$var wire 1 $ s0 $end
$var wire 1 % c4 $end
$var reg 1 & a0 $end
$var reg 1 ' a1 $end
$var reg 1 ( a2 $end
$var reg 1 ) a3 $end
$var reg 1 * b0 $end
$var reg 1 + b1 $end
$var reg 1 , b2 $end
$var reg 1 - b3 $end
$var reg 1 . c0 $end
$scope module test $end
$var wire 1 / G1 $end
$var wire 1 & a0 $end
$var wire 1 ' a1 $end
$var wire 1 ( a2 $end
$var wire 1 ) a3 $end
$var wire 1 * b0 $end
$var wire 1 + b1 $end
$var wire 1 , b2 $end
$var wire 1 - b3 $end
$var wire 1 . c0 $end
$var wire 1 0 c1 $end
$var wire 1 1 c2 $end
$var wire 1 2 c3 $end
$var wire 1 % c4 $end
$var wire 1 3 g0 $end
$var wire 1 4 g1 $end
$var wire 1 5 g2 $end
$var wire 1 6 g3 $end
$var wire 1 7 p0 $end
$var wire 1 8 p1 $end
$var wire 1 9 p2 $end
$var wire 1 : p3 $end
$var wire 1 $ s0 $end
$var wire 1 # s1 $end
$var wire 1 " s2 $end
$var wire 1 ! s3 $end
$var wire 1 ; t1 $end
$var wire 1 < t10 $end
$var wire 1 = t11 $end
$var wire 1 > t12 $end
$var wire 1 ? t13 $end
$var wire 1 @ t14 $end
$var wire 1 A t15 $end
$var wire 1 B t16 $end
$var wire 1 C t2 $end
$var wire 1 D t3 $end
$var wire 1 E t4 $end
$var wire 1 F t5 $end
$var wire 1 G t6 $end
$var wire 1 H t7 $end
$var wire 1 I t8 $end
$var wire 1 J t9 $end
$upscope $end
$upscope $end
$enddefinitions $end
#0
$dumpvars
0J
0I
0H
0G
0F
xE
0D
0C
0B
0A
0@
0?
0>
0=
0<
0;
0:
09
08
07
06
05
04
03
02
x1
00
z/
0.
0-
0,
0+
0*
0)
0(
0'
0&
0%
0$
0#
x"
0!
$end
#5
1$
17
1&
#10
0&
1*
#15
1#
0$
10
07
13
1&
#20
00
1#
03
18
0&
0*
1'
#25
1$
17
1&
#30
0&
1*
#35
1"
11
0#
1E
0$
10
1D
07
13
1&
#40
x"
x1
1#
xE
00
0D
03
0&
0*
0'
1+
#45
1$
17
1&
#50
0&
1*
#55
1"
11
0#
1E
0$
10
1D
07
13
1&
#60
x"
x1
xE
00
0D
0#
03
08
14
0&
0*
1'
#65
1$
17
1&
#70
0&
1*
#75
1#
0$
10
07
13
1&
#80
0#
00
03
04
19
0&
0*
0'
0+
1(
#85
1$
17
1&
#90
0&
1*
#95
1#
0$
10
07
13
1&
#100
00
1#
03
18
0&
0*
1'
#105
1$
17
1&
#110
0&
1*
#115
0"
1!
11
12
0#
1E
1J
0$
10
1D
1G
07
13
1&
#120
x"
0!
x1
02
1#
xE
0J
00
0D
0G
03
0&
0*
0'
1+
#125
1$
17
1&
#130
0&
1*
#135
0"
1!
11
12
0#
1E
1J
0$
10
1D
1G
07
13
1&
#140
x"
x1
xE
1I
00
0D
0G
0#
1H
03
08
14
0&
0*
1'
#145
1$
17
1&
#150
0&
1*
#155
1#
0$
10
07
13
1&
#160
0!
02
0J
0#
0I
00
0H
03
04
0&
0*
0'
0+
0(
1,
#165
1$
17
1&
#170
0&
1*
#175
1#
0$
10
07
13
1&
#180
00
1#
03
18
0&
0*
1'
#185
1$
17
1&
#190
0&
1*
#195
0"
1!
11
12
0#
1E
1J
0$
10
1D
1G
07
13
1&
#200
x"
0!
x1
02
1#
xE
0J
00
0D
0G
03
0&
0*
0'
1+
#205
1$
17
1&
#210
0&
1*
#215
0"
1!
11
12
0#
1E
1J
0$
10
1D
1G
07
13
1&
#220
x"
x1
xE
1I
00
0D
0G
0#
1H
03
08
14
0&
0*
1'
#225
1$
17
1&
#230
0&
1*
#235
1#
0$
10
07
13
1&
#240
0#
00
0H
03
04
09
15
0&
0*
0'
0+
1(
#245
1$
17
1&
#250
0&
1*
#255
1#
0$
10
07
13
1&
#260
00
1#
03
18
0&
0*
1'
#265
1$
17
1&
#270
0&
1*
#275
1"
11
0#
1E
0$
10
1D
07
13
1&
#280
x"
x1
1#
xE
00
0D
03
0&
0*
0'
1+
#285
1$
17
1&
#290
0&
1*
#295
1"
11
0#
1E
0$
10
1D
07
13
1&
#300
x"
x1
xE
00
0D
0#
03
08
14
0&
0*
1'
#305
1$
17
1&
#310
0&
1*
#315
1#
0$
10
07
13
1&
#320
02
0#
0J
00
0I
1!
03
04
05
1:
0&
0*
0'
0+
0(
0,
1)
#325
1$
17
1&
#330
0&
1*
#335
1#
0$
10
07
13
1&
#340
00
1#
03
18
0&
0*
1'
#345
1$
17
1&
#350
0&
1*
#355
1"
11
0#
1E
0$
10
1D
07
13
1&
#360
x"
x1
1#
xE
00
0D
03
0&
0*
0'
1+
#365
1$
17
1&
#370
0&
1*
#375
1"
11
0#
1E
0$
10
1D
07
13
1&
#380
x"
x1
xE
00
0D
0#
03
08
14
0&
0*
1'
#385
1$
17
1&
#390
0&
1*
#395
1#
0$
10
07
13
1&
#400
0#
00
03
04
19
0&
0*
0'
0+
1(
#405
1$
17
1&
#410
0&
1*
#415
1#
0$
10
07
13
1&
#420
00
1#
03
18
0&
0*
1'
#425
1$
17
1&
#430
0&
1*
#435
0"
0!
11
12
1%
0#
1E
1J
1B
0$
10
1D
1G
1=
07
13
1&
#440
x"
1!
x1
02
0%
1#
xE
0J
0B
00
0D
0G
0=
03
0&
0*
0'
1+
#445
1$
17
1&
#450
0&
1*
#455
0"
0!
11
12
1%
0#
1E
1J
1B
0$
10
1D
1G
1=
07
13
1&
#460
x"
x1
xE
1I
1A
00
0D
0G
0=
0#
1H
1>
03
08
14
0&
0*
1'
#465
1$
17
1&
#470
0&
1*
#475
1#
0$
10
07
13
1&
#480
1!
02
0%
0J
0B
0#
0I
0A
00
0H
0>
03
04
0&
0*
0'
0+
0(
1,
#485
1$
17
1&
#490
0&
1*
#495
1#
0$
10
07
13
1&
#500
00
1#
03
18
0&
0*
1'
#505
1$
17
1&
#510
0&
1*
#515
0"
0!
11
12
1%
0#
1E
1J
1B
0$
10
1D
1G
1=
07
13
1&
#520
x"
1!
x1
02
0%
1#
xE
0J
0B
00
0D
0G
0=
03
0&
0*
0'
1+
#525
1$
17
1&
#530
0&
1*
#535
0"
0!
11
12
1%
0#
1E
1J
1B
0$
10
1D
1G
1=
07
13
1&
#540
x"
x1
xE
1I
1A
00
0D
0G
0=
0#
1H
1>
03
08
14
0&
0*
1'
#545
1$
17
1&
#550
0&
1*
#555
1#
0$
10
07
13
1&
#560
0#
1@
00
0H
0>
1?
03
04
09
15
0&
0*
0'
0+
1(
#565
1$
17
1&
#570
0&
1*
#575
1#
0$
10
07
13
1&
#580
00
1#
03
18
0&
0*
1'
#585
1$
17
1&
#590
0&
1*
#595
1"
11
0#
1E
0$
10
1D
07
13
1&
#600
x"
x1
1#
xE
00
0D
03
0&
0*
0'
1+
#605
1$
17
1&
#610
0&
1*
#615
1"
11
0#
1E
0$
10
1D
07
13
1&
#620
x"
x1
xE
00
0D
0#
03
08
14
0&
0*
1'
#625
1$
17
1&
#630
0&
1*
#635
1#
0$
10
07
13
1&
#640
0%
1!
0B
02
0A
0#
0J
0@
00
0I
0?
03
04
05
0&
0*
0'
0+
0(
0,
0)
1-
#645
1$
17
1&
#650
0&
1*
#655
1#
0$
10
07
13
1&
#660
00
1#
03
18
0&
0*
1'
#665
1$
17
1&
#670
0&
1*
#675
1"
11
0#
1E
0$
10
1D
07
13
1&
#680
x"
x1
1#
xE
00
0D
03
0&
0*
0'
1+
#685
1$
17
1&
#690
0&
1*
#695
1"
11
0#
1E
0$
10
1D
07
13
1&
#700
x"
x1
xE
00
0D
0#
03
08
14
0&
0*
1'
#705
1$
17
1&
#710
0&
1*
#715
1#
0$
10
07
13
1&
#720
0#
00
03
04
19
0&
0*
0'
0+
1(
#725
1$
17
1&
#730
0&
1*
#735
1#
0$
10
07
13
1&
#740
00
1#
03
18
0&
0*
1'
#745
1$
17
1&
#750
0&
1*
#755
0"
0!
11
12
1%
0#
1E
1J
1B
0$
10
1D
1G
1=
07
13
1&
#760
x"
1!
x1
02
0%
1#
xE
0J
0B
00
0D
0G
0=
03
0&
0*
0'
1+
#765
1$
17
1&
#770
0&
1*
#775
0"
0!
11
12
1%
0#
1E
1J
1B
0$
10
1D
1G
1=
07
13
1&
#780
x"
x1
xE
1I
1A
00
0D
0G
0=
0#
1H
1>
03
08
14
0&
0*
1'
#785
1$
17
1&
#790
0&
1*
#795
1#
0$
10
07
13
1&
#800
1!
02
0%
0J
0B
0#
0I
0A
00
0H
0>
03
04
0&
0*
0'
0+
0(
1,
#805
1$
17
1&
#810
0&
1*
#815
1#
0$
10
07
13
1&
#820
00
1#
03
18
0&
0*
1'
#825
1$
17
1&
#830
0&
1*
#835
0"
0!
11
12
1%
0#
1E
1J
1B
0$
10
1D
1G
1=
07
13
1&
#840
x"
1!
x1
02
0%
1#
xE
0J
0B
00
0D
0G
0=
03
0&
0*
0'
1+
#845
1$
17
1&
#850
0&
1*
#855
0"
0!
11
12
1%
0#
1E
1J
1B
0$
10
1D
1G
1=
07
13
1&
#860
x"
x1
xE
1I
1A
00
0D
0G
0=
0#
1H
1>
03
08
14
0&
0*
1'
#865
1$
17
1&
#870
0&
1*
#875
1#
0$
10
07
13
1&
#880
0#
1@
00
0H
0>
1?
03
04
09
15
0&
0*
0'
0+
1(
#885
1$
17
1&
#890
0&
1*
#895
1#
0$
10
07
13
1&
#900
00
1#
03
18
0&
0*
1'
#905
1$
17
1&
#910
0&
1*
#915
1"
11
0#
1E
0$
10
1D
07
13
1&
#920
x"
x1
1#
xE
00
0D
03
0&
0*
0'
1+
#925
1$
17
1&
#930
0&
1*
#935
1"
11
0#
1E
0$
10
1D
07
13
1&
#940
x"
x1
xE
00
0D
0#
03
08
14
0&
0*
1'
#945
1$
17
1&
#950
0&
1*
#955
1#
0$
10
07
13
1&
#960
02
0#
0J
00
0I
0?
0!
03
04
05
0:
16
0&
0*
0'
0+
0(
0,
1)
#965
1$
17
1&
#970
0&
1*
#975
1#
0$
10
07
13
1&
#980
00
1#
03
18
0&
0*
1'
#985
1$
17
1&
#990
0&
1*
#995
1"
11
0#
1E
0$
10
1D
07
13
1&
#1000
x"
x1
1#
xE
00
0D
03
0&
0*
0'
1+
#1005
1$
17
1&
#1010
0&
1*
#1015
1"
11
0#
1E
0$
10
1D
07
13
1&
#1020
x"
x1
xE
00
0D
0#
03
08
14
0&
0*
1'
#1025
1$
17
1&
#1030
0&
1*
#1035
1#
0$
10
07
13
1&
#1040
0#
00
03
04
19
0&
0*
0'
0+
1(
#1045
1$
17
1&
#1050
0&
1*
#1055
1#
0$
10
07
13
1&
#1060
00
1#
03
18
0&
0*
1'
#1065
1$
17
1&
#1070
0&
1*
#1075
0"
1!
11
12
0#
1E
1J
0$
10
1D
1G
07
13
1&
#1080
x"
0!
x1
02
1#
xE
0J
00
0D
0G
03
0&
0*
0'
1+
#1085
1$
17
1&
#1090
0&
1*
#1095
0"
1!
11
12
0#
1E
1J
0$
10
1D
1G
07
13
1&
#1100
x"
x1
xE
1I
00
0D
0G
0#
1H
03
08
14
0&
0*
1'
#1105
1$
17
1&
#1110
0&
1*
#1115
1#
0$
10
07
13
1&
#1120
0!
02
0J
0#
0I
00
0H
03
04
0&
0*
0'
0+
0(
1,
#1125
1$
17
1&
#1130
0&
1*
#1135
1#
0$
10
07
13
1&
#1140
00
1#
03
18
0&
0*
1'
#1145
1$
17
1&
#1150
0&
1*
#1155
0"
1!
11
12
0#
1E
1J
0$
10
1D
1G
07
13
1&
#1160
x"
0!
x1
02
1#
xE
0J
00
0D
0G
03
0&
0*
0'
1+
#1165
1$
17
1&
#1170
0&
1*
#1175
0"
1!
11
12
0#
1E
1J
0$
10
1D
1G
07
13
1&
#1180
x"
x1
xE
1I
00
0D
0G
0#
1H
03
08
14
0&
0*
1'
#1185
1$
17
1&
#1190
0&
1*
#1195
1#
0$
10
07
13
1&
#1200
0#
00
0H
03
04
09
15
0&
0*
0'
0+
1(
#1205
1$
17
1&
#1210
0&
1*
#1215
1#
0$
10
07
13
1&
#1220
00
1#
03
18
0&
0*
1'
#1225
1$
17
1&
#1230
0&
1*
#1235
1"
11
0#
1E
0$
10
1D
07
13
1&
#1240
x"
x1
1#
xE
00
0D
03
0&
0*
0'
1+
#1245
1$
17
1&
#1250
0&
1*
#1255
1"
11
0#
1E
0$
10
1D
07
13
1&
#1260
x"
x1
xE
00
0D
0#
03
08
14
0&
0*
1'
#1265
1$
17
1&
#1270
0&
1*
#1275
1#
0$
10
07
13
1&
#1280
0!
0%
02
0B
0#
0J
0A
00
0I
0@
03
04
05
06
1$
0&
0*
0'
0+
0(
0,
0)
0-
1.
#1285
1#
10
1;
0$
17
1&
#1290
0&
1*
#1295
0;
1$
07
13
1&
#1300
00
1#
03
18
0&
0*
1'
#1305
0#
1"
10
11
1;
1C
0$
17
1&
#1310
0&
1*
#1315
1E
0;
0C
1$
1D
07
13
1&
#1320
x"
x1
1#
xE
00
0D
03
0&
0*
0'
1+
#1325
0#
1"
10
11
1;
1C
0$
17
1&
#1330
0&
1*
#1335
1E
0;
0C
1$
1D
07
13
1&
#1340
x"
x1
xE
00
0D
0#
03
08
14
0&
0*
1'
#1345
1#
10
1;
0$
17
1&
#1350
0&
1*
#1355
0;
1$
07
13
1&
#1360
0#
00
03
04
19
0&
0*
0'
0+
1(
#1365
1#
10
1;
0$
17
1&
#1370
0&
1*
#1375
0;
1$
07
13
1&
#1380
00
1#
03
18
0&
0*
1'
#1385
0#
0"
1!
10
11
12
1;
1C
1F
0$
17
1&
#1390
0&
1*
#1395
1E
1J
0;
0C
0F
1$
1D
1G
07
13
1&
#1400
x"
0!
x1
02
1#
xE
0J
00
0D
0G
03
0&
0*
0'
1+
#1405
0#
0"
1!
10
11
12
1;
1C
1F
0$
17
1&
#1410
0&
1*
#1415
1E
1J
0;
0C
0F
1$
1D
1G
07
13
1&
#1420
x"
x1
xE
1I
00
0D
0G
0#
1H
03
08
14
0&
0*
1'
#1425
1#
10
1;
0$
17
1&
#1430
0&
1*
#1435
0;
1$
07
13
1&
#1440
0!
02
0J
0#
0I
00
0H
03
04
0&
0*
0'
0+
0(
1,
#1445
1#
10
1;
0$
17
1&
#1450
0&
1*
#1455
0;
1$
07
13
1&
#1460
00
1#
03
18
0&
0*
1'
#1465
0#
0"
1!
10
11
12
1;
1C
1F
0$
17
1&
#1470
0&
1*
#1475
1E
1J
0;
0C
0F
1$
1D
1G
07
13
1&
#1480
x"
0!
x1
02
1#
xE
0J
00
0D
0G
03
0&
0*
0'
1+
#1485
0#
0"
1!
10
11
12
1;
1C
1F
0$
17
1&
#1490
0&
1*
#1495
1E
1J
0;
0C
0F
1$
1D
1G
07
13
1&
#1500
x"
x1
xE
1I
00
0D
0G
0#
1H
03
08
14
0&
0*
1'
#1505
1#
10
1;
0$
17
1&
#1510
0&
1*
#1515
0;
1$
07
13
1&
#1520
0#
00
0H
03
04
09
15
0&
0*
0'
0+
1(
#1525
1#
10
1;
0$
17
1&
#1530
0&
1*
#1535
0;
1$
07
13
1&
#1540
00
1#
03
18
0&
0*
1'
#1545
0#
1"
10
11
1;
1C
0$
17
1&
#1550
0&
1*
#1555
1E
0;
0C
1$
1D
07
13
1&
#1560
x"
x1
1#
xE
00
0D
03
0&
0*
0'
1+
#1565
0#
1"
10
11
1;
1C
0$
17
1&
#1570
0&
1*
#1575
1E
0;
0C
1$
1D
07
13
1&
#1580
x"
x1
xE
00
0D
0#
03
08
14
0&
0*
1'
#1585
1#
10
1;
0$
17
1&
#1590
0&
1*
#1595
0;
1$
07
13
1&
#1600
02
0#
0J
00
0I
1!
03
04
05
1:
0&
0*
0'
0+
0(
0,
1)
#1605
1#
10
1;
0$
17
1&
#1610
0&
1*
#1615
0;
1$
07
13
1&
#1620
00
1#
03
18
0&
0*
1'
#1625
0#
1"
10
11
1;
1C
0$
17
1&
#1630
0&
1*
#1635
1E
0;
0C
1$
1D
07
13
1&
#1640
x"
x1
1#
xE
00
0D
03
0&
0*
0'
1+
#1645
0#
1"
10
11
1;
1C
0$
17
1&
#1650
0&
1*
#1655
1E
0;
0C
1$
1D
07
13
1&
#1660
x"
x1
xE
00
0D
0#
03
08
14
0&
0*
1'
#1665
1#
10
1;
0$
17
1&
#1670
0&
1*
#1675
0;
1$
07
13
1&
#1680
0#
00
03
04
19
0&
0*
0'
0+
1(
#1685
1#
10
1;
0$
17
1&
#1690
0&
1*
#1695
0;
1$
07
13
1&
#1700
00
1#
03
18
0&
0*
1'
#1705
0#
0"
0!
1%
10
11
12
1<
1;
1C
1F
0$
17
1&
#1710
0&
1*
#1715
0<
1E
1J
1B
0;
0C
0F
1$
1D
1G
1=
07
13
1&
#1720
x"
1!
x1
02
0%
1#
xE
0J
0B
00
0D
0G
0=
03
0&
0*
0'
1+
#1725
0#
0"
0!
1%
10
11
12
1<
1;
1C
1F
0$
17
1&
#1730
0&
1*
#1735
0<
1E
1J
1B
0;
0C
0F
1$
1D
1G
1=
07
13
1&
#1740
x"
x1
xE
1I
1A
00
0D
0G
0=
0#
1H
1>
03
08
14
0&
0*
1'
#1745
1#
10
1;
0$
17
1&
#1750
0&
1*
#1755
0;
1$
07
13
1&
#1760
1!
02
0%
0J
0B
0#
0I
0A
00
0H
0>
03
04
0&
0*
0'
0+
0(
1,
#1765
1#
10
1;
0$
17
1&
#1770
0&
1*
#1775
0;
1$
07
13
1&
#1780
00
1#
03
18
0&
0*
1'
#1785
0#
0"
0!
1%
10
11
12
1<
1;
1C
1F
0$
17
1&
#1790
0&
1*
#1795
0<
1E
1J
1B
0;
0C
0F
1$
1D
1G
1=
07
13
1&
#1800
x"
1!
x1
02
0%
1#
xE
0J
0B
00
0D
0G
0=
03
0&
0*
0'
1+
#1805
0#
0"
0!
1%
10
11
12
1<
1;
1C
1F
0$
17
1&
#1810
0&
1*
#1815
0<
1E
1J
1B
0;
0C
0F
1$
1D
1G
1=
07
13
1&
#1820
x"
x1
xE
1I
1A
00
0D
0G
0=
0#
1H
1>
03
08
14
0&
0*
1'
#1825
1#
10
1;
0$
17
1&
#1830
0&
1*
#1835
0;
1$
07
13
1&
#1840
0#
1@
00
0H
0>
1?
03
04
09
15
0&
0*
0'
0+
1(
#1845
1#
10
1;
0$
17
1&
#1850
0&
1*
#1855
0;
1$
07
13
1&
#1860
00
1#
03
18
0&
0*
1'
#1865
0#
1"
10
11
1;
1C
0$
17
1&
#1870
0&
1*
#1875
1E
0;
0C
1$
1D
07
13
1&
#1880
x"
x1
1#
xE
00
0D
03
0&
0*
0'
1+
#1885
0#
1"
10
11
1;
1C
0$
17
1&
#1890
0&
1*
#1895
1E
0;
0C
1$
1D
07
13
1&
#1900
x"
x1
xE
00
0D
0#
03
08
14
0&
0*
1'
#1905
1#
10
1;
0$
17
1&
#1910
0&
1*
#1915
0;
1$
07
13
1&
#1920
0%
1!
0B
02
0A
0#
0J
0@
00
0I
0?
03
04
05
0&
0*
0'
0+
0(
0,
0)
1-
#1925
1#
10
1;
0$
17
1&
#1930
0&
1*
#1935
0;
1$
07
13
1&
#1940
00
1#
03
18
0&
0*
1'
#1945
0#
1"
10
11
1;
1C
0$
17
1&
#1950
0&
1*
#1955
1E
0;
0C
1$
1D
07
13
1&
#1960
x"
x1
1#
xE
00
0D
03
0&
0*
0'
1+
#1965
0#
1"
10
11
1;
1C
0$
17
1&
#1970
0&
1*
#1975
1E
0;
0C
1$
1D
07
13
1&
#1980
x"
x1
xE
00
0D
0#
03
08
14
0&
0*
1'
#1985
1#
10
1;
0$
17
1&
#1990
0&
1*
#1995
0;
1$
07
13
1&
#2000
0#
00
03
04
19
0&
0*
0'
0+
1(
#2005
1#
10
1;
0$
17
1&
#2010
0&
1*
#2015
0;
1$
07
13
1&
#2020
00
1#
03
18
0&
0*
1'
#2025
0#
0"
0!
1%
10
11
12
1<
1;
1C
1F
0$
17
1&
#2030
0&
1*
#2035
0<
1E
1J
1B
0;
0C
0F
1$
1D
1G
1=
07
13
1&
#2040
x"
1!
x1
02
0%
1#
xE
0J
0B
00
0D
0G
0=
03
0&
0*
0'
1+
#2045
0#
0"
0!
1%
10
11
12
1<
1;
1C
1F
0$
17
1&
#2050
0&
1*
#2055
0<
1E
1J
1B
0;
0C
0F
1$
1D
1G
1=
07
13
1&
#2060
x"
x1
xE
1I
1A
00
0D
0G
0=
0#
1H
1>
03
08
14
0&
0*
1'
#2065
1#
10
1;
0$
17
1&
#2070
0&
1*
#2075
0;
1$
07
13
1&
#2080
1!
02
0%
0J
0B
0#
0I
0A
00
0H
0>
03
04
0&
0*
0'
0+
0(
1,
#2085
1#
10
1;
0$
17
1&
#2090
0&
1*
#2095
0;
1$
07
13
1&
#2100
00
1#
03
18
0&
0*
1'
#2105
0#
0"
0!
1%
10
11
12
1<
1;
1C
1F
0$
17
1&
#2110
0&
1*
#2115
0<
1E
1J
1B
0;
0C
0F
1$
1D
1G
1=
07
13
1&
#2120
x"
1!
x1
02
0%
1#
xE
0J
0B
00
0D
0G
0=
03
0&
0*
0'
1+
#2125
0#
0"
0!
1%
10
11
12
1<
1;
1C
1F
0$
17
1&
#2130
0&
1*
#2135
0<
1E
1J
1B
0;
0C
0F
1$
1D
1G
1=
07
13
1&
#2140
x"
x1
xE
1I
1A
00
0D
0G
0=
0#
1H
1>
03
08
14
0&
0*
1'
#2145
1#
10
1;
0$
17
1&
#2150
0&
1*
#2155
0;
1$
07
13
1&
#2160
0#
1@
00
0H
0>
1?
03
04
09
15
0&
0*
0'
0+
1(
#2165
1#
10
1;
0$
17
1&
#2170
0&
1*
#2175
0;
1$
07
13
1&
#2180
00
1#
03
18
0&
0*
1'
#2185
0#
1"
10
11
1;
1C
0$
17
1&
#2190
0&
1*
#2195
1E
0;
0C
1$
1D
07
13
1&
#2200
x"
x1
1#
xE
00
0D
03
0&
0*
0'
1+
#2205
0#
1"
10
11
1;
1C
0$
17
1&
#2210
0&
1*
#2215
1E
0;
0C
1$
1D
07
13
1&
#2220
x"
x1
xE
00
0D
0#
03
08
14
0&
0*
1'
#2225
1#
10
1;
0$
17
1&
#2230
0&
1*
#2235
0;
1$
07
13
1&
#2240
02
0#
0J
00
0I
0?
0!
03
04
05
0:
16
0&
0*
0'
0+
0(
0,
1)
#2245
1#
10
1;
0$
17
1&
#2250
0&
1*
#2255
0;
1$
07
13
1&
#2260
00
1#
03
18
0&
0*
1'
#2265
0#
1"
10
11
1;
1C
0$
17
1&
#2270
0&
1*
#2275
1E
0;
0C
1$
1D
07
13
1&
#2280
x"
x1
1#
xE
00
0D
03
0&
0*
0'
1+
#2285
0#
1"
10
11
1;
1C
0$
17
1&
#2290
0&
1*
#2295
1E
0;
0C
1$
1D
07
13
1&
#2300
x"
x1
xE
00
0D
0#
03
08
14
0&
0*
1'
#2305
1#
10
1;
0$
17
1&
#2310
0&
1*
#2315
0;
1$
07
13
1&
#2320
0#
00
03
04
19
0&
0*
0'
0+
1(
#2325
1#
10
1;
0$
17
1&
#2330
0&
1*
#2335
0;
1$
07
13
1&
#2340
00
1#
03
18
0&
0*
1'
#2345
0#
0"
1!
10
11
12
1;
1C
1F
0$
17
1&
#2350
0&
1*
#2355
1E
1J
0;
0C
0F
1$
1D
1G
07
13
1&
#2360
x"
0!
x1
02
1#
xE
0J
00
0D
0G
03
0&
0*
0'
1+
#2365
0#
0"
1!
10
11
12
1;
1C
1F
0$
17
1&
#2370
0&
1*
#2375
1E
1J
0;
0C
0F
1$
1D
1G
07
13
1&
#2380
x"
x1
xE
1I
00
0D
0G
0#
1H
03
08
14
0&
0*
1'
#2385
1#
10
1;
0$
17
1&
#2390
0&
1*
#2395
0;
1$
07
13
1&
#2400
0!
02
0J
0#
0I
00
0H
03
04
0&
0*
0'
0+
0(
1,
#2405
1#
10
1;
0$
17
1&
#2410
0&
1*
#2415
0;
1$
07
13
1&
#2420
00
1#
03
18
0&
0*
1'
#2425
0#
0"
1!
10
11
12
1;
1C
1F
0$
17
1&
#2430
0&
1*
#2435
1E
1J
0;
0C
0F
1$
1D
1G
07
13
1&
#2440
x"
0!
x1
02
1#
xE
0J
00
0D
0G
03
0&
0*
0'
1+
#2445
0#
0"
1!
10
11
12
1;
1C
1F
0$
17
1&
#2450
0&
1*
#2455
1E
1J
0;
0C
0F
1$
1D
1G
07
13
1&
#2460
x"
x1
xE
1I
00
0D
0G
0#
1H
03
08
14
0&
0*
1'
#2465
1#
10
1;
0$
17
1&
#2470
0&
1*
#2475
0;
1$
07
13
1&
#2480
0#
00
0H
03
04
09
15
0&
0*
0'
0+
1(
#2485
1#
10
1;
0$
17
1&
#2490
0&
1*
#2495
0;
1$
07
13
1&
#2500
00
1#
03
18
0&
0*
1'
#2505
0#
1"
10
11
1;
1C
0$
17
1&
#2510
0&
1*
#2515
1E
0;
0C
1$
1D
07
13
1&
#2520
x"
x1
1#
xE
00
0D
03
0&
0*
0'
1+
#2525
0#
1"
10
11
1;
1C
0$
17
1&
#2530
0&
1*
#2535
1E
0;
0C
1$
1D
07
13
1&
#2540
x"
x1
xE
00
0D
0#
03
08
14
0&
0*
1'
#2545
1#
10
1;
0$
17
1&
#2550
0&
1*
#2555
0;
1$
07
13
1&
#2560
0!
0%
02
0B
0#
0J
0A
00
0I
0@
03
04
05
06
0$
0&
0*
0'
0+
0(
0,
0)
0-
0.
